MANIFEST.in
cupy_setup_build.py
setup.cfg
setup.py
cupy/__init__.py
cupy/_version.py
cupy/cudnn.cpp
cupy/cusparse.py
cupy/internal.py
cupy/util.cpp
cupy/binary/__init__.py
cupy/binary/elementwise.py
cupy/binary/packing.py
cupy/core/__init__.py
cupy/core/core.cpp
cupy/core/flags.cpp
cupy/core/fusion.py
cupy/core/internal.cpp
cupy/core/include/cupy/atomics.cuh
cupy/core/include/cupy/carray.cuh
cupy/core/include/cupy/complex.cuh
cupy/core/include/cupy/complex/arithmetic.h
cupy/core/include/cupy/complex/catrig.h
cupy/core/include/cupy/complex/catrigf.h
cupy/core/include/cupy/complex/ccosh.h
cupy/core/include/cupy/complex/ccoshf.h
cupy/core/include/cupy/complex/cexp.h
cupy/core/include/cupy/complex/cexpf.h
cupy/core/include/cupy/complex/clog.h
cupy/core/include/cupy/complex/clogf.h
cupy/core/include/cupy/complex/complex.h
cupy/core/include/cupy/complex/complex_inl.h
cupy/core/include/cupy/complex/cpow.h
cupy/core/include/cupy/complex/cproj.h
cupy/core/include/cupy/complex/csinh.h
cupy/core/include/cupy/complex/csinhf.h
cupy/core/include/cupy/complex/csqrt.h
cupy/core/include/cupy/complex/csqrtf.h
cupy/core/include/cupy/complex/ctanh.h
cupy/core/include/cupy/complex/ctanhf.h
cupy/core/include/cupy/complex/math_private.h
cupy/creation/__init__.py
cupy/creation/basic.py
cupy/creation/from_data.py
cupy/creation/matrix.py
cupy/creation/ranges.py
cupy/cuda/__init__.py
cupy/cuda/compiler.py
cupy/cuda/cublas.cpp
cupy/cuda/cudnn.cpp
cupy/cuda/cudnn_util.py
cupy/cuda/cufft.cpp
cupy/cuda/cupy_common.h
cupy/cuda/cupy_cuComplex.h
cupy/cuda/cupy_cuda.h
cupy/cuda/cupy_cudnn.h
cupy/cuda/cupy_cufft.h
cupy/cuda/cupy_cusolver.h
cupy/cuda/cupy_cusparse.h
cupy/cuda/cupy_nccl.h
cupy/cuda/cupy_nvrtc.h
cupy/cuda/cupy_stdint.h
cupy/cuda/cupy_thrust.cu
cupy/cuda/cupy_thrust.h
cupy/cuda/curand.cpp
cupy/cuda/cusolver.cpp
cupy/cuda/cusparse.cpp
cupy/cuda/device.cpp
cupy/cuda/driver.cpp
cupy/cuda/function.cpp
cupy/cuda/memory.cpp
cupy/cuda/memory_hook.cpp
cupy/cuda/nccl.cpp
cupy/cuda/nvrtc.cpp
cupy_ibmopt.egg-info/PKG-INFO
cupy_ibmopt.egg-info/SOURCES.txt
cupy_ibmopt.egg-info/dependency_links.txt
cupy_ibmopt.egg-info/not-zip-safe
cupy_ibmopt.egg-info/requires.txt
cupy_ibmopt.egg-info/top_level.txt
