Metadata-Version: 1.0
Name: cupy-ibmopt
Version: 4.0.0a3
Summary: CuPy: NumPy-like API accelerated with CUDA (opbimized for POWER machines by IBM)
Home-page: https://docs-cupy.chainer.org/
Author: Seiya Tokui
Author-email: tokui@preferred.jp
License: MIT License
Platform: UNKNOWN
